.dj-config.json
dj/__init__.py
dj/__main__.py
dj/config_loader.py
dj/objects.py
dj/process_runner.py
dj_command-0.5.2.dist-info/entry_points.txt
dj_command-0.5.2.dist-info/LICENSE
dj_command-0.5.2.dist-info/WHEEL
dj_command-0.5.2.dist-info/METADATA
dj_command-0.5.2.dist-info/RECORD
