Metadata-Version: 2.1
Name: dj-command
Version: 0.5.2
Summary: Run commands with `dj {command_name}`. Uses aliases defined in a simple config file or defaults to Django management commands.
Home-page: https://github.com/adamghill/dj
Author: Adam Hill
Author-email: adamghill@yahoo.com
Requires-Python: >=3.6,<4.0
Classifier: Programming Language :: Python :: 3
Classifier: Programming Language :: Python :: 3.6
Classifier: Programming Language :: Python :: 3.7
Requires-Dist: attrs (>=19.1,<20.0)
Requires-Dist: click (>=7.0,<8.0)
Requires-Dist: colorama (>=0.4.1,<0.5.0)
Requires-Dist: delegator.py (>=0.1.1,<0.2.0)
Requires-Dist: python-dotenv (>=0.10.3,<0.11.0)
Requires-Dist: toml (>=0.10.0,<0.11.0)
Project-URL: Repository, https://github.com/adamghill/dj
